luckyrandom/__init__.py
luckyrandom-0.0.3.dist-info/LICENSE
luckyrandom-0.0.3.dist-info/METADATA
luckyrandom-0.0.3.dist-info/WHEEL
luckyrandom-0.0.3.dist-info/top_level.txt
luckyrandom-0.0.3.dist-info/RECORD
