Metadata-Version: 2.1
Name: luckyrandom
Version: 0.0.3
Summary: Encourage users with bad luck
Home-page: https://github.com/maxesisn/luckyrandom
Author: Maximilian Wu
Author-email: me@maxesisn.online
License: UNKNOWN
Platform: UNKNOWN
Classifier: Programming Language :: Python :: 3
Classifier: License :: OSI Approved :: GNU General Public License v3 (GPLv3)
Classifier: Operating System :: OS Independent
Requires-Python: >=3.6
